{
  "lesson_id": "losing-iron-condor",
  "title": "Losing Iron Condor (What Went Wrong)",
  "estimated_time": "8 min",
  "total_xp": 80,
  "badge": "📉 Lesson Learned",
  "screens": [
    {"screen_type": "hook", "visual": "warning_red.png", "headline": "I lost $300 by ignoring one rule.", "text": "Close when your stop hits."},
    {"screen_type": "definition", "headline": "Meet Mike", "text": "1 year trading | $25k account | Premium seller. Loves iron condors; mistake: hope trading.", "visual": "trader_card_mike.png"},
    {"screen_type": "definition", "headline": "The Trade (Feb 1, 2024)", "text": "SPY $490. Sold $530/535 call spread (+$1.50) and $470/465 put spread (+$1.50) → $3.00 credit. Max profit $300; max loss $200; profit zone $467–$533 (13.2% wide).", "visual": "condor_diagram.png"},
    {"screen_type": "key_terms", "headline": "The Plan (ignored)", "cards": [
      {"term": "Target", "definition": "Close at 50% profit ($150)"},
      {"term": "Stop", "definition": "Close at $4.00 (−$100)"},
      {"term": "Adjustment", "definition": "Roll tested side when breached"}
    ]},
    {"screen_type": "scenario", "headline": "The Disaster Timeline", "question": "Week-by-week", "options": [
      "W1: SPY 495; value $1.70 (up $130)",
      "W2: SPY 503; value $2.50 (−$50)",
      "W3: SPY 509; value $4.20 (−$220) — STOP HIT",
      "W4: SPY 514; value $4.80 (−$280); Exp: SPY 515 → max loss"], "correct": 2, "xp_reward": 10, "explanation_correct": "Ignoring stop converted small loss into max loss.", "explanation_wrong": "The stop was the moment to act."},
    {"screen_type": "analogy", "headline": "Decision Point (Day 16)", "text": "Choices: A) Close (−$220), B) Roll tested calls, C) Close untested puts, D) Hope (what he did). Loss aversion + hope = larger losses."},
    {"screen_type": "key_terms", "headline": "What Went Right (few)", "cards": [
      {"term": "Range", "definition": "13% wide; reasonable"},
      {"term": "Sizing", "definition": "Risk $200 (0.8% of account)"}
    ]},
    {"screen_type": "key_terms", "headline": "What Went Wrong (many)", "cards": [
      {"term": "Ignored Stop", "definition": "Rule said −$100; held to −$200"},
      {"term": "No Adjustment", "definition": "Could roll tested side"},
      {"term": "Held to Expiry", "definition": "Hoping for miracle"},
      {"term": "Didn’t De-risk", "definition": "Could close untested side to cut risk"}
    ]},
    {"screen_type": "summary_cards", "headline": "Takeaway", "cards": [
      {"front": "Stop = stop", "back": "Not ‘stop and think’"},
      {"front": "Act early", "back": "Small loss < max loss"},
      {"front": "Plan → Action", "back": "Write rules and follow them"}
    ]},
    {"screen_type": "celebration", "xp_earned": 80, "total_xp": 80, "badge": "📉 Lesson Learned", "badge_description": "Follow stops without hesitation", "streak_bonus": false, "celebration_message": "The tuition was $200—lesson is priceless.", "next_lesson_preview": {"title": "Perfect Vertical Spread Timing", "description": "Catalyst + conviction + structure", "unlock_status": "unlocked"}}
  ]
}


